MANIFEST.in
setup.py
django_grappelli_extensions.egg-info/PKG-INFO
django_grappelli_extensions.egg-info/SOURCES.txt
django_grappelli_extensions.egg-info/dependency_links.txt
django_grappelli_extensions.egg-info/requires.txt
django_grappelli_extensions.egg-info/top_level.txt
grappelli_extensions/__init__.py
grappelli_extensions/models.py
grappelli_extensions/navbar.py
grappelli_extensions/nodes.py
grappelli_extensions/test_navbar.py
grappelli_extensions/test_settings.py
grappelli_extensions/test_urls.py
grappelli_extensions/static/css/grappelli_extensions.css
grappelli_extensions/static/css/journal.css
grappelli_extensions/static/less/journal.less
grappelli_extensions/static/less/variables.less
grappelli_extensions/templates/admin/base.html
grappelli_extensions/templates/grappelli/navbar.html
grappelli_extensions/templates/grappelli/sidebar.html
grappelli_extensions/templatetags/__init__.py
grappelli_extensions/templatetags/grappelli_navbar.py